{
  "string": [
    {
      "name": "module_desc",
      "value": "module description"
    },
    {
      "name": "EntryAbility_desc",
      "value": "description"
    },
    {
      "name": "EntryAbility_label",
      "value": "Sweet Video"
    },
    {
      "name": "sure",
      "value": "Sure"
    },
    {
      "name": "cancel",
      "value": "Cancel"
    },
    {
      "name": "rename",
      "value": "Rename"
    },
    {
      "name": "search",
      "value": "Search"
    },
    {
      "name": "set_passwd",
      "value": "Set password"
    },
    {
      "name": "entered_privacy_space",
      "value": "Entered privacy space"
    },
    {
      "name": "set_passwd_tip",
      "value": "Password has been changed! Enter the password in the search box to enter the privacy space"
    },
    {
      "name": "nothing",
      "value": "Do Not Go Gentle into That Good Night"
    },
    {
      "name": "add_video_first",
      "value": "Add video first"
    },
    {
      "name": "close_rotation_lock",
      "value": "Rotation lock closed"
    },
    {
      "name": "open_rotation_lock",
      "value": "Rotation lock opened"
    },
    {
      "name": "no_search_result",
      "value": "No search result"
    },
    {
      "name": "unknown_size",
      "value": "Unknown size"
    },
    {
      "name": "del_confirm",
      "value": "Do you want to delete the video?"
    },
    {
      "name": "edit",
      "value": "Edit"
    },
    {
      "name": "delete",
      "value": "Delete"
    },
    {
      "name": "import_from_files",
      "value": "Import from files"
    },
    {
      "name": "import_from_album",
      "value": "Import from albums"
    },
    {
      "name": "open_side_bar_tip",
      "value": "Swipe left or click the button in the top left corner to add the first video!"
    },
    {
      "name": "unknown_resolution",
      "value": "Unknown resolution"
    },
    {
      "name": "video_error",
      "value": "Video Error! May not play properly"
    }
  ]
}